{
  "RSpec": {
    "coverage": {
      "/Users/sage/Turing/1_mod/projects/night_writer/spec/night_writer_spec.rb": {
        "lines": [
          1,
          null,
          1,
          6,
          null,
          1,
          1,
          null,
          null,
          1,
          1,
          1,
          1,
          null,
          null,
          1,
          1,
          null,
          null,
          1,
          1,
          1,
          null,
          null,
          1,
          1,
          1,
          1,
          null,
          1,
          null,
          1,
          1,
          null,
          null
        ]
      },
      "/Users/sage/Turing/1_mod/projects/night_writer/spec/spec_helper.rb": {
        "lines": [
          1,
          1,
          1,
          1,
          1,
          null,
          null,
          1,
          null
        ]
      }
    },
    "timestamp": 1663958529
  }
}
